aaudd/__init__.py
aaudd/aaudd.py
aaudd-4.0.dist-info/LICENSE
aaudd-4.0.dist-info/METADATA
aaudd-4.0.dist-info/WHEEL
aaudd-4.0.dist-info/entry_points.txt
aaudd-4.0.dist-info/top_level.txt
aaudd-4.0.dist-info/RECORD
