Metadata-Version: 2.1
Name: aaudd
Version: 4.0
Summary: Script for audio recognition using AUDD API
Home-page: https://twitter.com/Lanaev0li
Author: Avinion
Author-email: shizofrin@gmail.com
License: 
Classifier: Programming Language :: Python :: 3
Classifier: License :: OSI Approved :: MIT License
Classifier: Operating System :: OS Independent
License-File: LICENSE
Requires-Dist: requests
